openevolve/__init__.py
openevolve/_version.py
openevolve/api.py
openevolve/cli.py
openevolve/config.py
openevolve/controller.py
openevolve/database.py
openevolve/evaluation_result.py
openevolve/evaluator.py
openevolve/evolution_trace.py
openevolve/iteration.py
openevolve/process_parallel.py
openevolve/py.typed
openevolve/llm/__init__.py
openevolve/llm/base.py
openevolve/llm/dummy.py
openevolve/llm/ensemble.py
openevolve/llm/openai.py
openevolve/prompt/__init__.py
openevolve/prompt/sampler.py
openevolve/prompt/templates.py
openevolve/prompts/defaults/diff_user.txt
openevolve/prompts/defaults/evaluation.txt
openevolve/prompts/defaults/evaluator_system_message.txt
openevolve/prompts/defaults/evolution_history.txt
openevolve/prompts/defaults/fragments.json
openevolve/prompts/defaults/full_rewrite_user.txt
openevolve/prompts/defaults/inspiration_program.txt
openevolve/prompts/defaults/inspirations_section.txt
openevolve/prompts/defaults/previous_attempt.txt
openevolve/prompts/defaults/system_message.txt
openevolve/prompts/defaults/top_program.txt
openevolve/utils/__init__.py
openevolve/utils/async_utils.py
openevolve/utils/code_utils.py
openevolve/utils/format_utils.py
openevolve/utils/metrics_utils.py
openevolve/utils/trace_export_utils.py
openevolve_ext_env-0.2.17.3.dist-info/licenses/LICENSE
openevolve_visualizer/__init__.py
openevolve_visualizer/visualizer.py
openevolve_visualizer/static/css/main.css
openevolve_visualizer/static/js/graph.js
openevolve_visualizer/static/js/list.js
openevolve_visualizer/static/js/main.js
openevolve_visualizer/static/js/mainUI.js
openevolve_visualizer/static/js/performance.js
openevolve_visualizer/static/js/sidebar.js
openevolve_visualizer/static/js/state.js
openevolve_visualizer/templates/index.html
openevolve_visualizer/templates/program_page.html
openevolve_ext_env-0.2.17.3.dist-info/METADATA
openevolve_ext_env-0.2.17.3.dist-info/WHEEL
openevolve_ext_env-0.2.17.3.dist-info/entry_points.txt
openevolve_ext_env-0.2.17.3.dist-info/top_level.txt
openevolve_ext_env-0.2.17.3.dist-info/RECORD
